voxelworldapi/__init__.py
voxelworldapi/voxelworldapi.py
voxelworldapi-1.35.post20240601.dist-info/LICENSE
voxelworldapi-1.35.post20240601.dist-info/METADATA
voxelworldapi-1.35.post20240601.dist-info/WHEEL
voxelworldapi-1.35.post20240601.dist-info/top_level.txt
voxelworldapi-1.35.post20240601.dist-info/RECORD
