Metadata-Version: 2.1
Name: voxelworldapi
Version: 1.35.post20240601
Summary: A Python library for interacting with VoxelWorld API
Home-page: https://github.com/callfishxt/voxelworldapi
Author: CallFish
Author-email: callfish@mail.ru
License: MIT
License-File: LICENSE
Requires-Dist: requests
